MANIFEST.in
README.txt
setup.cfg
setup.py
django_videos.egg-info/PKG-INFO
django_videos.egg-info/SOURCES.txt
django_videos.egg-info/dependency_links.txt
django_videos.egg-info/entry_points.txt
django_videos.egg-info/not-zip-safe
django_videos.egg-info/top_level.txt
djangovideos/__init__.py
djangovideos/admin.py
djangovideos/forms.py
djangovideos/models.py
djangovideos/urls.py
djangovideos/views.py
djangovideos/templates/djangovideos/add.html
djangovideos/templates/djangovideos/add_form.html
djangovideos/templates/djangovideos/base.html
djangovideos/templates/djangovideos/delete_link.html
djangovideos/templates/djangovideos/video.html
djangovideos/templatetags/__init__.py
djangovideos/templatetags/video_tags.py
djangovideos/tests/__init__.py
djangovideos/tests/functionnal.py
djangovideos/tests/test_index.py