Metadata-Version: 1.0
Name: django-videos
Version: 0.1
Summary: Add some youtube videos to your django app
Home-page: http://packages.python.org/django-videos/
Author: Bearstech
Author-email: gpasgrimaud@bearstech.com
License: GPL
Keywords: django youtube
Platform: UNKNOWN
